edc_unblinding/__init__.py
edc_unblinding/action_items.py
edc_unblinding/admin_site.py
edc_unblinding/apps.py
edc_unblinding/auth_objects.py
edc_unblinding/auths.py
edc_unblinding/constants.py
edc_unblinding/urls.py
edc_unblinding/admin/__init__.py
edc_unblinding/admin/autocomplete_admin.py
edc_unblinding/admin/unblinding_request_admin.py
edc_unblinding/admin/unblinding_review_admin.py
edc_unblinding/forms/__init__.py
edc_unblinding/forms/unblinding_request_form.py
edc_unblinding/forms/unblinding_review_form.py
edc_unblinding/migrations/0001_initial.py
edc_unblinding/migrations/0002_auto_20210908_2318.py
edc_unblinding/migrations/0003_auto_20210911_2036.py
edc_unblinding/migrations/0004_auto_20220704_1841.py
edc_unblinding/migrations/0005_alter_historicalunblindingrequest_action_identifier_and_more.py
edc_unblinding/migrations/0006_auto_20220826_0258.py
edc_unblinding/migrations/0007_auto_20220826_0322.py
edc_unblinding/migrations/0008_auto_20220826_0406.py
edc_unblinding/migrations/0009_alter_unblindingrequest_managers_and_more.py
edc_unblinding/migrations/0010_alter_historicalunblindingrequest_device_created_and_more.py
edc_unblinding/migrations/0011_alter_unblindingrequest_options_and_more.py
edc_unblinding/migrations/0012_alter_historicalunblindingrequest_site_and_more.py
edc_unblinding/migrations/__init__.py
edc_unblinding/models/__init__.py
edc_unblinding/models/unblinding_request.py
edc_unblinding/models/unblinding_review.py
edc_unblinding/models/unblinding_user.py
edc_unblinding/tests/__init__.py
edc_unblinding/tests/holidays.csv
edc_unblinding/tests/models.py
edc_unblinding/tests/test_settings.py
edc_unblinding/tests/urls.py
edc_unblinding/tests/etc/user-aes-local.key
edc_unblinding/tests/etc/user-aes-restricted.key
edc_unblinding/tests/etc/user-rsa-local-private.pem
edc_unblinding/tests/etc/user-rsa-local-public.pem
edc_unblinding/tests/etc/user-rsa-restricted-private.pem
edc_unblinding/tests/etc/user-rsa-restricted-public.pem
edc_unblinding-1.0.2.dist-info/licenses/AUTHORS
edc_unblinding-1.0.2.dist-info/licenses/LICENSE
edc_unblinding-1.0.2.dist-info/METADATA
edc_unblinding-1.0.2.dist-info/WHEEL
edc_unblinding-1.0.2.dist-info/top_level.txt
edc_unblinding-1.0.2.dist-info/RECORD
